[
  {
    "inputs": [
      {
        "internalType": "address",
        "name": "_proxyToClone",
        "type": "address"
      },
      {
        "internalType": "uint256",
        "name": "_fee",
        "type": "uint256"
      }
    ],
    "payable": false,
    "stateMutability": "nonpayable",
    "type": "constructor"
  },
  {
    "constant": false,
    "inputs": [
      {
        "internalType": "contract IMarket",
        "name": "_market",
        "type": "address"
      },
      {
        "internalType": "contract IParaShareToken",
        "name": "_para",
        "type": "address"
      }
    ],
    "name": "addAMM",
    "outputs": [
      {
        "internalType": "contract AMMExchange",
        "name": "",
        "type": "address"
      }
    ],
    "payable": false,
    "stateMutability": "nonpayable",
    "type": "function"
  },
  {
    "constant": true,
    "inputs": [
      {
        "internalType": "address",
        "name": "target",
        "type": "address"
      },
      {
        "internalType": "uint256",
        "name": "salt",
        "type": "uint256"
      },
      {
        "internalType": "address",
        "name": "creator",
        "type": "address"
      }
    ],
    "name": "clone2Address",
    "outputs": [
      {
        "internalType": "address",
        "name": "",
        "type": "address"
      }
    ],
    "payable": false,
    "stateMutability": "pure",
    "type": "function"
  },
  {
    "constant": true,
    "inputs": [
      {
        "internalType": "address",
        "name": "",
        "type": "address"
      },
      {
        "internalType": "address",
        "name": "",
        "type": "address"
      }
    ],
    "name": "exchanges",
    "outputs": [
      {
        "internalType": "address",
        "name": "",
        "type": "address"
      }
    ],
    "payable": false,
    "stateMutability": "view",
    "type": "function"
  },
  {
    "constant": true,
    "inputs": [],
    "name": "fee",
    "outputs": [
      {
        "internalType": "uint256",
        "name": "",
        "type": "uint256"
      }
    ],
    "payable": false,
    "stateMutability": "view",
    "type": "function"
  },
  {
    "constant": true,
    "inputs": [
      {
        "internalType": "contract IMarket",
        "name": "_market",
        "type": "address"
      },
      {
        "internalType": "contract IParaShareToken",
        "name": "_para",
        "type": "address"
      }
    ],
    "name": "salt",
    "outputs": [
      {
        "internalType": "uint256",
        "name": "",
        "type": "uint256"
      }
    ],
    "payable": false,
    "stateMutability": "pure",
    "type": "function"
  }
]
